img2term/__init__.py
img2term/img2term.py
img2term-0.1.3.dist-info/licenses/LICENSE
img2term-0.1.3.dist-info/METADATA
img2term-0.1.3.dist-info/WHEEL
img2term-0.1.3.dist-info/entry_points.txt
img2term-0.1.3.dist-info/top_level.txt
img2term-0.1.3.dist-info/RECORD
