Metadata-Version: 2.4
Name: img2term
Version: 0.1.3
Summary: Display an image in your terminal
Author-email: Mike Wang <mike.wang7@gmail.com>
License: Unlicense
Project-URL: Homepage, https://github.com/myswang/img2term
Project-URL: Repository, https://github.com/myswang/img2term
Requires-Python: >=3.8
License-File: LICENSE
Requires-Dist: pillow
Dynamic: license-file
